[
    {
        "id": "b9607baf28665f27",
        "type": "mqtt out",
        "z": "77be3b95a6ef09ab",
        "name": "",
        "topic": "esp8266/output1",
        "qos": "2",
        "retain": "",
        "respTopic": "",
        "contentType": "",
        "userProps": "",
        "correl": "",
        "expiry": "",
        "broker": "57180ba4093cb330",
        "x": 260,
        "y": 480,
        "wires": []
    },
    {
        "id": "ce71fc0dc0ec4774",
        "type": "mqtt out",
        "z": "77be3b95a6ef09ab",
        "name": "",
        "topic": "esp8266/output2",
        "qos": "2",
        "retain": "",
        "respTopic": "",
        "contentType": "",
        "userProps": "",
        "correl": "",
        "expiry": "",
        "broker": "57180ba4093cb330",
        "x": 270,
        "y": 520,
        "wires": []
    },
    {
        "id": "590df73e9c474a65",
        "type": "ui_switch",
        "z": "77be3b95a6ef09ab",
        "name": "",
        "label": "led1",
        "tooltip": "",
        "group": "8a92ef6bfd9410e5",
        "order": 3,
        "width": 0,
        "height": 0,
        "passthru": true,
        "decouple": "false",
        "topic": "topic",
        "topicType": "msg",
        "style": "",
        "onvalue": "on",
        "onvalueType": "str",
        "onicon": "",
        "oncolor": "",
        "offvalue": "off",
        "offvalueType": "str",
        "officon": "",
        "offcolor": "",
        "animate": false,
        "x": 70,
        "y": 480,
        "wires": [
            [
                "b9607baf28665f27"
            ]
        ]
    },
    {
        "id": "4499a141ffb243b9",
        "type": "ui_switch",
        "z": "77be3b95a6ef09ab",
        "name": "",
        "label": "led2",
        "tooltip": "",
        "group": "8a92ef6bfd9410e5",
        "order": 4,
        "width": 0,
        "height": 0,
        "passthru": true,
        "decouple": "false",
        "topic": "topic",
        "topicType": "msg",
        "style": "",
        "onvalue": "on",
        "onvalueType": "str",
        "onicon": "",
        "oncolor": "",
        "offvalue": "off",
        "offvalueType": "str",
        "officon": "",
        "offcolor": "",
        "animate": false,
        "x": 70,
        "y": 520,
        "wires": [
            [
                "ce71fc0dc0ec4774"
            ]
        ]
    },
    {
        "id": "57180ba4093cb330",
        "type": "mqtt-broker",
        "name": "",
        "broker": "mosquitto",
        "port": "1883",
        "clientid": "",
        "usetls": false,
        "protocolVersion": "4",
        "keepalive": "60",
        "cleansession": true,
        "birthTopic": "",
        "birthQos": "0",
        "birthPayload": "",
        "birthMsg": {},
        "closeTopic": "",
        "closeQos": "0",
        "closePayload": "",
        "closeMsg": {},
        "willTopic": "",
        "willQos": "0",
        "willPayload": "",
        "willMsg": {},
        "sessionExpiry": ""
    },
    {
        "id": "8a92ef6bfd9410e5",
        "type": "ui_group",
        "name": "Default",
        "tab": "70df625f18569beb",
        "order": 1,
        "disp": true,
        "width": "6",
        "collapse": false
    },
    {
        "id": "70df625f18569beb",
        "type": "ui_tab",
        "name": "Home",
        "icon": "dashboard",
        "disabled": false,
        "hidden": false
    }
]